prefect_google_sheets/__init__.py
prefect_google_sheets/_version.py
prefect_google_sheets/blocks.py
prefect_google_sheets/exceptions.py
prefect_google_sheets/tasks.py
prefect_google_sheets/utils/__init__.py
prefect_google_sheets/utils/dataframe.py
prefect_google_sheets/utils/google.py
prefect_google_sheets-0.1.1.dist-info/LICENSE
prefect_google_sheets-0.1.1.dist-info/METADATA
prefect_google_sheets-0.1.1.dist-info/WHEEL
prefect_google_sheets-0.1.1.dist-info/entry_points.txt
prefect_google_sheets-0.1.1.dist-info/top_level.txt
prefect_google_sheets-0.1.1.dist-info/RECORD
